ecmwf_models/__init__.py
ecmwf_models/cli.py
ecmwf_models/extract.py
ecmwf_models/globals.py
ecmwf_models/grid.py
ecmwf_models/interface.py
ecmwf_models/utils.py
ecmwf_models/era5/__init__.py
ecmwf_models/era5/download.py
ecmwf_models/era5/era5-land_lut.csv
ecmwf_models/era5/era5_lut.csv
ecmwf_models/era5/img.py
ecmwf_models/era5/reshuffle.py
ecmwf_models/era5/land_definition_files/landmask_0.1_0.1.nc
ecmwf_models/era5/land_definition_files/landmask_0.25_0.25.nc
ecmwf_models-0.11.1.dist-info/licenses/AUTHORS.rst
ecmwf_models-0.11.1.dist-info/licenses/LICENSE.txt
ecmwf_models-0.11.1.dist-info/METADATA
ecmwf_models-0.11.1.dist-info/WHEEL
ecmwf_models-0.11.1.dist-info/entry_points.txt
ecmwf_models-0.11.1.dist-info/top_level.txt
ecmwf_models-0.11.1.dist-info/RECORD
