Metadata-Version: 2.4
Name: ecmwf_models
Version: 0.11.1
Summary: Downloading, reading and TS conversion of ECMWF reanalysis data
Author-email: TU Wien <support@qa4sm.eu>
License: mit
Project-URL: Homepage, https://github.com/TUW-GEO/ecmwf_models/
Project-URL: Documentation, https://ecmwf-models.readthedocs.io/en/latest/
Classifier: Development Status :: 4 - Beta
Classifier: Programming Language :: Python
Requires-Python: >=3.6
License-File: LICENSE.txt
License-File: AUTHORS.rst
Requires-Dist: importlib-metadata; python_version < "3.8"
Requires-Dist: numpy>=2
Requires-Dist: pandas
Requires-Dist: netcdf4
Requires-Dist: click
Requires-Dist: parse
Requires-Dist: pygrib
Requires-Dist: xarray
Requires-Dist: c3s_sm>=0.3.1
Requires-Dist: cdsapi>=0.7.3
Requires-Dist: repurpose>=0.13
Requires-Dist: pygeogrids
Provides-Extra: testing
Requires-Dist: pytest-cov; extra == "testing"
Requires-Dist: coverage; extra == "testing"
Requires-Dist: pytest; extra == "testing"
Provides-Extra: building
Requires-Dist: setuptools>=46.1.0; extra == "building"
Requires-Dist: setuptools_scm[toml]>=5; extra == "building"
Requires-Dist: wheel; extra == "building"
Requires-Dist: packaging; extra == "building"
Requires-Dist: build; extra == "building"
Requires-Dist: twine; extra == "building"
Provides-Extra: docs
Requires-Dist: sphinx<7,>=3.2.1; extra == "docs"
Requires-Dist: sphinx_rtd_theme; extra == "docs"
Requires-Dist: mock; extra == "docs"
Requires-Dist: pillow; extra == "docs"
Requires-Dist: recommonmark; extra == "docs"
Requires-Dist: readthedocs-sphinx-ext; extra == "docs"
Requires-Dist: myst_parser; extra == "docs"
Requires-Dist: nbsphinx; extra == "docs"
Dynamic: license-file
